[{"\ufeffA\u00d1O": "1995", "OPERACION": "Inspecciones forestales", "OPERACIONES_REALIZADAS_(NUMERO)": "745"}, {"\ufeffA\u00d1O": "1995", "OPERACION": "Operativos de inspeccion", "OPERACIONES_REALIZADAS_(NUMERO)": "53"}, {"\ufeffA\u00d1O": "1995", "OPERACION": "Resoluciones forestales", "OPERACIONES_REALIZADAS_(NUMERO)": "654"}, {"\ufeffA\u00d1O": "1996", "OPERACION": "Inspecciones forestales", "OPERACIONES_REALIZADAS_(NUMERO)": "5673"}, {"\ufeffA\u00d1O": "1996", "OPERACION": "Operativos de inspeccion", "OPERACIONES_REALIZADAS_(NUMERO)": "337"}, {"\ufeffA\u00d1O": "1996", "OPERACION": "Resoluciones forestales", "OPERACIONES_REALIZADAS_(NUMERO)": "1318"}, {"\ufeffA\u00d1O": "1997", "OPERACION": "Inspecciones forestales", "OPERACIONES_REALIZADAS_(NUMERO)": "7957"}, {"\ufeffA\u00d1O": "1997", "OPERACION": "Operativos de inspeccion", "OPERACIONES_REALIZADAS_(NUMERO)": "1031"}, {"\ufeffA\u00d1O": "1997", "OPERACION": "Resoluciones forestales", "OPERACIONES_REALIZADAS_(NUMERO)": "1439"}, {"\ufeffA\u00d1O": "1998", "OPERACION": "Inspecciones forestales", "OPERACIONES_REALIZADAS_(NUMERO)": "5650"}, {"\ufeffA\u00d1O": "1998", "OPERACION": "Operativos de inspeccion", "OPERACIONES_REALIZADAS_(NUMERO)": "1013"}, {"\ufeffA\u00d1O": "1998", "OPERACION": "Resoluciones forestales", "OPERACIONES_REALIZADAS_(NUMERO)": "3002"}, {"\ufeffA\u00d1O": "1999", "OPERACION": "Inspecciones forestales", "OPERACIONES_REALIZADAS_(NUMERO)": "5189"}, {"\ufeffA\u00d1O": "1999", "OPERACION": "Operativos de inspeccion", "OPERACIONES_REALIZADAS_(NUMERO)": "2006"}, {"\ufeffA\u00d1O": "1999", "OPERACION": "Resoluciones forestales", "OPERACIONES_REALIZADAS_(NUMERO)": "4484"}, {"\ufeffA\u00d1O": "2000", "OPERACION": "Inspecciones forestales", "OPERACIONES_REALIZADAS_(NUMERO)": "6011"}, {"\ufeffA\u00d1O": "2000", "OPERACION": "Operativos de inspeccion", "OPERACIONES_REALIZADAS_(NUMERO)": "1015"}, {"\ufeffA\u00d1O": "2000", "OPERACION": "Resoluciones forestales", "OPERACIONES_REALIZADAS_(NUMERO)": "5288"}, {"\ufeffA\u00d1O": "2001", "OPERACION": "Inspecciones forestales", "OPERACIONES_REALIZADAS_(NUMERO)": "6207"}, {"\ufeffA\u00d1O": "2001", "OPERACION": "Operativos de inspeccion", "OPERACIONES_REALIZADAS_(NUMERO)": "734"}, {"\ufeffA\u00d1O": "2001", "OPERACION": "Resoluciones forestales", "OPERACIONES_REALIZADAS_(NUMERO)": "6516"}, {"\ufeffA\u00d1O": "2002", "OPERACION": "Inspecciones forestales", "OPERACIONES_REALIZADAS_(NUMERO)": "7020"}, {"\ufeffA\u00d1O": "2002", "OPERACION": "Operativos de inspeccion", "OPERACIONES_REALIZADAS_(NUMERO)": "180"}, {"\ufeffA\u00d1O": "2002", "OPERACION": "Resoluciones forestales", "OPERACIONES_REALIZADAS_(NUMERO)": "4256"}, {"\ufeffA\u00d1O": "2003", "OPERACION": "Inspecciones forestales", "OPERACIONES_REALIZADAS_(NUMERO)": "7420"}, {"\ufeffA\u00d1O": "2003", "OPERACION": "Operativos de inspeccion", "OPERACIONES_REALIZADAS_(NUMERO)": "98"}, {"\ufeffA\u00d1O": "2003", "OPERACION": "Resoluciones forestales", "OPERACIONES_REALIZADAS_(NUMERO)": "14253"}, {"\ufeffA\u00d1O": "2004", "OPERACION": "Inspecciones forestales", "OPERACIONES_REALIZADAS_(NUMERO)": "7570"}, {"\ufeffA\u00d1O": "2004", "OPERACION": "Operativos de inspeccion", "OPERACIONES_REALIZADAS_(NUMERO)": "167"}, {"\ufeffA\u00d1O": "2004", "OPERACION": "Resoluciones forestales", "OPERACIONES_REALIZADAS_(NUMERO)": "3567"}, {"\ufeffA\u00d1O": "2005", "OPERACION": "Inspecciones forestales", "OPERACIONES_REALIZADAS_(NUMERO)": "7015"}, {"\ufeffA\u00d1O": "2005", "OPERACION": "Operativos de inspeccion", "OPERACIONES_REALIZADAS_(NUMERO)": "165"}, {"\ufeffA\u00d1O": "2005", "OPERACION": "Resoluciones forestales", "OPERACIONES_REALIZADAS_(NUMERO)": "3152"}, {"\ufeffA\u00d1O": "2006", "OPERACION": "Inspecciones forestales", "OPERACIONES_REALIZADAS_(NUMERO)": "6437"}, {"\ufeffA\u00d1O": "2006", "OPERACION": "Operativos de inspeccion", "OPERACIONES_REALIZADAS_(NUMERO)": "94"}, {"\ufeffA\u00d1O": "2006", "OPERACION": "Resoluciones forestales", "OPERACIONES_REALIZADAS_(NUMERO)": "2797"}, {"\ufeffA\u00d1O": "2007", "OPERACION": "Inspecciones forestales", "OPERACIONES_REALIZADAS_(NUMERO)": "6902"}, {"\ufeffA\u00d1O": "2007", "OPERACION": "Operativos de inspeccion", "OPERACIONES_REALIZADAS_(NUMERO)": "197"}, {"\ufeffA\u00d1O": "2007", "OPERACION": "Resoluciones forestales", "OPERACIONES_REALIZADAS_(NUMERO)": "4385"}, {"\ufeffA\u00d1O": "2008", "OPERACION": "Inspecciones forestales", "OPERACIONES_REALIZADAS_(NUMERO)": "6994"}, {"\ufeffA\u00d1O": "2008", "OPERACION": "Operativos de inspeccion", "OPERACIONES_REALIZADAS_(NUMERO)": "132"}, {"\ufeffA\u00d1O": "2008", "OPERACION": "Resoluciones forestales", "OPERACIONES_REALIZADAS_(NUMERO)": "3047"}, {"\ufeffA\u00d1O": "2009", "OPERACION": "Inspecciones forestales", "OPERACIONES_REALIZADAS_(NUMERO)": "7448"}, {"\ufeffA\u00d1O": "2009", "OPERACION": "Operativos de inspeccion", "OPERACIONES_REALIZADAS_(NUMERO)": "166"}, {"\ufeffA\u00d1O": "2009", "OPERACION": "Resoluciones forestales", "OPERACIONES_REALIZADAS_(NUMERO)": "3544"}, {"\ufeffA\u00d1O": "2010", "OPERACION": "Inspecciones forestales", "OPERACIONES_REALIZADAS_(NUMERO)": "5857"}, {"\ufeffA\u00d1O": "2010", "OPERACION": "Operativos de inspeccion", "OPERACIONES_REALIZADAS_(NUMERO)": "185"}, {"\ufeffA\u00d1O": "2010", "OPERACION": "Resoluciones forestales", "OPERACIONES_REALIZADAS_(NUMERO)": "3355"}, {"\ufeffA\u00d1O": "2011", "OPERACION": "Inspecciones forestales", "OPERACIONES_REALIZADAS_(NUMERO)": "5684"}, {"\ufeffA\u00d1O": "2011", "OPERACION": "Operativos de inspeccion", "OPERACIONES_REALIZADAS_(NUMERO)": "312"}, {"\ufeffA\u00d1O": "2011", "OPERACION": "Resoluciones forestales", "OPERACIONES_REALIZADAS_(NUMERO)": "5830"}, {"\ufeffA\u00d1O": "2012", "OPERACION": "Inspecciones forestales", "OPERACIONES_REALIZADAS_(NUMERO)": "3794"}, {"\ufeffA\u00d1O": "2012", "OPERACION": "Operativos de inspeccion", "OPERACIONES_REALIZADAS_(NUMERO)": "373"}, {"\ufeffA\u00d1O": "2012", "OPERACION": "Resoluciones forestales", "OPERACIONES_REALIZADAS_(NUMERO)": "3453"}, {"\ufeffA\u00d1O": "2013", "OPERACION": "Inspecciones forestales", "OPERACIONES_REALIZADAS_(NUMERO)": "4722"}, {"\ufeffA\u00d1O": "2013", "OPERACION": "Operativos de inspeccion", "OPERACIONES_REALIZADAS_(NUMERO)": "311"}, {"\ufeffA\u00d1O": "2013", "OPERACION": "Resoluciones forestales", "OPERACIONES_REALIZADAS_(NUMERO)": "3949"}, {"\ufeffA\u00d1O": "2014", "OPERACION": "Inspecciones forestales", "OPERACIONES_REALIZADAS_(NUMERO)": "4746"}, {"\ufeffA\u00d1O": "2014", "OPERACION": "Operativos de inspeccion", "OPERACIONES_REALIZADAS_(NUMERO)": "263"}, {"\ufeffA\u00d1O": "2014", "OPERACION": "Resoluciones forestales", "OPERACIONES_REALIZADAS_(NUMERO)": "4808"}, {"\ufeffA\u00d1O": "2015", "OPERACION": "Inspecciones forestales", "OPERACIONES_REALIZADAS_(NUMERO)": "3742"}, {"\ufeffA\u00d1O": "2015", "OPERACION": "Operativos de inspeccion", "OPERACIONES_REALIZADAS_(NUMERO)": "329"}, {"\ufeffA\u00d1O": "2015", "OPERACION": "Resoluciones forestales", "OPERACIONES_REALIZADAS_(NUMERO)": "3817"}]