[{"\ufeffA\u00d1O": "1993", "TIPO_DE_SUPERFICIE": "Incorporada", "EXTENSION_(HECTAREAS)": "14512"}, {"\ufeffA\u00d1O": "1993", "TIPO_DE_SUPERFICIE": "Acumulada", "EXTENSION_(HECTAREAS)": "14512"}, {"\ufeffA\u00d1O": "1994", "TIPO_DE_SUPERFICIE": "Incorporada", "EXTENSION_(HECTAREAS)": "42302"}, {"\ufeffA\u00d1O": "1994", "TIPO_DE_SUPERFICIE": "Acumulada", "EXTENSION_(HECTAREAS)": "56814"}, {"\ufeffA\u00d1O": "1995", "TIPO_DE_SUPERFICIE": "Incorporada", "EXTENSION_(HECTAREAS)": "64049"}, {"\ufeffA\u00d1O": "1995", "TIPO_DE_SUPERFICIE": "Acumulada", "EXTENSION_(HECTAREAS)": "120863"}, {"\ufeffA\u00d1O": "1996", "TIPO_DE_SUPERFICIE": "Incorporada", "EXTENSION_(HECTAREAS)": "109882"}, {"\ufeffA\u00d1O": "1996", "TIPO_DE_SUPERFICIE": "Acumulada", "EXTENSION_(HECTAREAS)": "230745"}, {"\ufeffA\u00d1O": "1997", "TIPO_DE_SUPERFICIE": "Incorporada", "EXTENSION_(HECTAREAS)": "139828"}, {"\ufeffA\u00d1O": "1997", "TIPO_DE_SUPERFICIE": "Acumulada", "EXTENSION_(HECTAREAS)": "370573"}, {"\ufeffA\u00d1O": "1998", "TIPO_DE_SUPERFICIE": "Incorporada", "EXTENSION_(HECTAREAS)": "200622"}, {"\ufeffA\u00d1O": "1998", "TIPO_DE_SUPERFICIE": "Acumulada", "EXTENSION_(HECTAREAS)": "571195"}, {"\ufeffA\u00d1O": "1999", "TIPO_DE_SUPERFICIE": "Incorporada", "EXTENSION_(HECTAREAS)": "225151"}, {"\ufeffA\u00d1O": "1999", "TIPO_DE_SUPERFICIE": "Acumulada", "EXTENSION_(HECTAREAS)": "796346"}, {"\ufeffA\u00d1O": "2000", "TIPO_DE_SUPERFICIE": "Incorporada", "EXTENSION_(HECTAREAS)": "240495"}, {"\ufeffA\u00d1O": "2000", "TIPO_DE_SUPERFICIE": "Acumulada", "EXTENSION_(HECTAREAS)": "1036841"}, {"\ufeffA\u00d1O": "2001", "TIPO_DE_SUPERFICIE": "Incorporada", "EXTENSION_(HECTAREAS)": "164823"}, {"\ufeffA\u00d1O": "2001", "TIPO_DE_SUPERFICIE": "Acumulada", "EXTENSION_(HECTAREAS)": "1201664"}, {"\ufeffA\u00d1O": "2002", "TIPO_DE_SUPERFICIE": "Incorporada", "EXTENSION_(HECTAREAS)": "224772"}, {"\ufeffA\u00d1O": "2002", "TIPO_DE_SUPERFICIE": "Acumulada", "EXTENSION_(HECTAREAS)": "1426436"}, {"\ufeffA\u00d1O": "2003", "TIPO_DE_SUPERFICIE": "Incorporada", "EXTENSION_(HECTAREAS)": "186716"}, {"\ufeffA\u00d1O": "2003", "TIPO_DE_SUPERFICIE": "Acumulada", "EXTENSION_(HECTAREAS)": "1613152"}, {"\ufeffA\u00d1O": "2004", "TIPO_DE_SUPERFICIE": "Incorporada", "EXTENSION_(HECTAREAS)": "195819"}, {"\ufeffA\u00d1O": "2004", "TIPO_DE_SUPERFICIE": "Acumulada", "EXTENSION_(HECTAREAS)": "1808971"}, {"\ufeffA\u00d1O": "2005", "TIPO_DE_SUPERFICIE": "Incorporada", "EXTENSION_(HECTAREAS)": "182674"}, {"\ufeffA\u00d1O": "2005", "TIPO_DE_SUPERFICIE": "Acumulada", "EXTENSION_(HECTAREAS)": "1991645"}, {"\ufeffA\u00d1O": "2006", "TIPO_DE_SUPERFICIE": "Incorporada", "EXTENSION_(HECTAREAS)": "212675"}, {"\ufeffA\u00d1O": "2006", "TIPO_DE_SUPERFICIE": "Acumulada", "EXTENSION_(HECTAREAS)": "2204320"}, {"\ufeffA\u00d1O": "2007", "TIPO_DE_SUPERFICIE": "Incorporada", "EXTENSION_(HECTAREAS)": "341376"}, {"\ufeffA\u00d1O": "2007", "TIPO_DE_SUPERFICIE": "Acumulada", "EXTENSION_(HECTAREAS)": "2545696"}, {"\ufeffA\u00d1O": "2008", "TIPO_DE_SUPERFICIE": "Incorporada", "EXTENSION_(HECTAREAS)": "373002"}, {"\ufeffA\u00d1O": "2008", "TIPO_DE_SUPERFICIE": "Acumulada", "EXTENSION_(HECTAREAS)": "2918698"}, {"\ufeffA\u00d1O": "2009", "TIPO_DE_SUPERFICIE": "Incorporada", "EXTENSION_(HECTAREAS)": "176904"}, {"\ufeffA\u00d1O": "2009", "TIPO_DE_SUPERFICIE": "Acumulada", "EXTENSION_(HECTAREAS)": "3095602"}, {"\ufeffA\u00d1O": "2010", "TIPO_DE_SUPERFICIE": "Incorporada", "EXTENSION_(HECTAREAS)": "265721"}, {"\ufeffA\u00d1O": "2010", "TIPO_DE_SUPERFICIE": "Acumulada", "EXTENSION_(HECTAREAS)": "3361323"}, {"\ufeffA\u00d1O": "2011", "TIPO_DE_SUPERFICIE": "Incorporada", "EXTENSION_(HECTAREAS)": "274495"}, {"\ufeffA\u00d1O": "2011", "TIPO_DE_SUPERFICIE": "Acumulada", "EXTENSION_(HECTAREAS)": "3635818"}, {"\ufeffA\u00d1O": "2012", "TIPO_DE_SUPERFICIE": "Incorporada", "EXTENSION_(HECTAREAS)": "422666"}, {"\ufeffA\u00d1O": "2012", "TIPO_DE_SUPERFICIE": "Acumulada", "EXTENSION_(HECTAREAS)": "4058484"}, {"\ufeffA\u00d1O": "2013", "TIPO_DE_SUPERFICIE": "Incorporada", "EXTENSION_(HECTAREAS)": "121006"}, {"\ufeffA\u00d1O": "2013", "TIPO_DE_SUPERFICIE": "Acumulada", "EXTENSION_(HECTAREAS)": "4179490"}, {"\ufeffA\u00d1O": "2014", "TIPO_DE_SUPERFICIE": "Incorporada", "EXTENSION_(HECTAREAS)": "128086"}, {"\ufeffA\u00d1O": "2014", "TIPO_DE_SUPERFICIE": "Acumulada", "EXTENSION_(HECTAREAS)": "4307576"}, {"\ufeffA\u00d1O": "2015", "TIPO_DE_SUPERFICIE": "Incorporada", "EXTENSION_(HECTAREAS)": "98691"}, {"\ufeffA\u00d1O": "2015", "TIPO_DE_SUPERFICIE": "Acumulada", "EXTENSION_(HECTAREAS)": "4406267"}]